jupyter_quant/__init__.py
jupyter_quant-2510.1.dist-info/licenses/LICENSE.txt
jupyter_quant-2510.1.dist-info/METADATA
jupyter_quant-2510.1.dist-info/WHEEL
jupyter_quant-2510.1.dist-info/top_level.txt
jupyter_quant-2510.1.dist-info/RECORD
