Metadata-Version: 2.4
Name: jupyter-quant
Version: 2510.1
Summary: Jupyter quant research environment. 
Author: gnzsnz
License-Expression: Apache-2.0
Project-URL: Homepage, https://github.com/quantbelt/jupyter-quant
Project-URL: Bug Tracker, https://github.com/quantbelt/jupyter-quant/issues
Classifier: Programming Language :: Python :: 3
Classifier: Operating System :: OS Independent
Classifier: Development Status :: 3 - Alpha
Requires-Python: >=3.10
License-File: LICENSE.txt
Requires-Dist: alphalens-reloaded==0.4.6
Requires-Dist: arch==7.2.0
Requires-Dist: black==25.9.0
Requires-Dist: bottleneck==1.6.0
Requires-Dist: dask[dataframe,distributed]==2025.10.0
Requires-Dist: empyrical-reloaded==0.5.12
Requires-Dist: exchange_calendars==4.11.2
Requires-Dist: h5py==3.15.1
Requires-Dist: hurst==0.0.5
Requires-Dist: ib-fundamental==0.0.5
Requires-Dist: ib_async==1.0.3
Requires-Dist: ipympl==0.9.8
Requires-Dist: ipywidgets==8.1.7
Requires-Dist: isort==7.0.0
Requires-Dist: jedi-language-server==0.45.1
Requires-Dist: jupyterlab==4.4.9
Requires-Dist: jupyterlab-lsp==5.2.0
Requires-Dist: jupyterlab_code_formatter==3.0.2
Requires-Dist: jupyterlab_widgets==3.0.15
Requires-Dist: lightgbm==4.6.0
Requires-Dist: matplotlib==3.10.7
Requires-Dist: numba==0.62.1
Requires-Dist: numexpr==2.14.1
Requires-Dist: numpy==2.2.6
Requires-Dist: optuna==4.5.0
Requires-Dist: pandas==2.3.3
Requires-Dist: patsy==1.0.1
Requires-Dist: pip==25.2
Requires-Dist: py_vollib==1.0.1
Requires-Dist: py_vollib_vectorized==0.1.1
Requires-Dist: pyarrow==21.0.0
Requires-Dist: pyfolio-reloaded==0.9.9
Requires-Dist: pykalman==0.10.2
Requires-Dist: PyPortfolioOpt==1.5.6
Requires-Dist: quantstats-lumi==1.0.1
Requires-Dist: scikit-learn==1.7.2
Requires-Dist: scipy==1.15.3
Requires-Dist: sdepy==1.2.0
Requires-Dist: seaborn==0.13.2
Requires-Dist: shap==0.49.1
Requires-Dist: statsmodels==0.14.5
Requires-Dist: TA-Lib==0.6.4
Requires-Dist: tzdata==2025.2
Requires-Dist: yellowbrick==1.5
Requires-Dist: yfinance==0.2.66
Requires-Dist: zipline-reloaded==3.1.1
Provides-Extra: sk-util
Requires-Dist: skfolio==0.14.1; extra == "sk-util"
Requires-Dist: sktime==0.39.0; extra == "sk-util"
Provides-Extra: bayes
Requires-Dist: arviz==0.22.0; extra == "bayes"
Requires-Dist: pymc==5.26.0; extra == "bayes"
Requires-Dist: formulae==0.5.4; extra == "bayes"
Requires-Dist: graphviz==0.21; extra == "bayes"
Provides-Extra: dev
Requires-Dist: pre-commit>=3.7.1; extra == "dev"
Requires-Dist: build; extra == "dev"
Requires-Dist: wheel; extra == "dev"
Requires-Dist: twine; extra == "dev"
Dynamic: license-file
